{
  "栃木県": {
    "_all": {
      "xlim": [
        0,
        393
      ],
      "ylim": [
        0,
        294
      ]
    },
    "小山市": {
      "xlim": [
        39,
        117
      ],
      "ylim": [
        68,
        157
      ]
    },
    "足利市": {
      "xlim": [
        118,
        196
      ],
      "ylim": [
        68,
        157
      ]
    },
    "大田原市": {
      "xlim": [
        237,
        314
      ],
      "ylim": [
        136,
        225
      ]
    },
    "那須烏山市": {
      "xlim": [
        315,
        393
      ],
      "ylim": [
        136,
        226
      ]
    },
    "さくら市": {
      "xlim": [
        79,
        157
      ],
      "ylim": [
        0,
        89
      ]
    },
    "壬生町": {
      "xlim": [
        197,
        275
      ],
      "ylim": [
        204,
        294
      ]
    },
    "日光市": {
      "xlim": [
        39,
        117
      ],
      "ylim": [
        204,
        294
      ]
    },
    "上三川町": {
      "xlim": [
        118,
        196
      ],
      "ylim": [
        204,
        294
      ]
    },
    "鹿沼市": {
      "xlim": [
        237,
        314
      ],
      "ylim": [
        0,
        89
      ]
    },
    "佐野市": {
      "xlim": [
        79,
        157
      ],
      "ylim": [
        136,
        226
      ]
    },
    "塩谷町": {
      "xlim": [
        158,
        236
      ],
      "ylim": [
        136,
        225
      ]
    },
    "那須町": {
      "xlim": [
        197,
        275
      ],
      "ylim": [
        68,
        157
      ]
    },
    "栃木市": {
      "xlim": [
        276,
        354
      ],
      "ylim": [
        68,
        157
      ]
    },
    "矢板市": {
      "xlim": [
        0,
        78
      ],
      "ylim": [
        136,
        226
      ]
    },
    "益子町": {
      "xlim": [
        158,
        236
      ],
      "ylim": [
        0,
        89
      ]
    }
  }
}